{
    "rounds": [
        {
            "roundNumber": 1,
            "scores": [
                {
                    "playerId": "jaseer",
                    "playerName": "Dada",
                    "score": 0
                },
                {
                    "playerId": "rashid",
                    "playerName": "Kuttappan",
                    "score": 9
                },
                {
                    "playerId": "Nasru",
                    "playerName": "Thiruppan",
                    "score": 9
                }
            ]
        },
        {
            "roundNumber": 2,
            "scores": [
                {
                    "playerId": "rashid",
                    "playerName": "Kuttappan",
                    "score": 0
                },
                {
                    "playerId": "Nasru",
                    "playerName": "Thiruppan",
                    "score": 14
                },
                {
                    "playerId": "jaseer",
                    "playerName": "Dada",
                    "score": 17
                }
            ]
        },
        {
            "roundNumber": 3,
            "scores": [
                {
                    "playerId": "jaseer",
                    "playerName": "Dada",
                    "score": 0
                },
                {
                    "playerId": "Nasru",
                    "playerName": "Thiruppan",
                    "score": 14
                },
                {
                    "playerId": "rashid",
                    "playerName": "Kuttappan",
                    "score": 16
                }
            ]
        },
        {
            "roundNumber": 4,
            "scores": [
                {
                    "playerId": "Nasru",
                    "playerName": "Thiruppan",
                    "score": 0
                },
                {
                    "playerId": "jaseer",
                    "playerName": "Dada",
                    "score": 11
                },
                {
                    "playerId": "rashid",
                    "playerName": "Kuttappan",
                    "score": 12
                }
            ]
        }
    ]
}